tree_comments/__init__.py
tree_comments/models.py
tree_comments/serializers.py
tree_comments/signals.py
tree_comments/viewsets.py
django_tree_comments-0.0.3.dist-info/LICENSE
django_tree_comments-0.0.3.dist-info/WHEEL
django_tree_comments-0.0.3.dist-info/METADATA
django_tree_comments-0.0.3.dist-info/RECORD
