Metadata-Version: 2.1
Name: django-tree-comments
Version: 0.0.3
Summary: A django library for building comments in tree structure.
Home-page: https://github.com/jukanntenn/django-tree-comments
License: BSD-3-Clause
Keywords: django
Author: jukanntenn
Author-email: jukanntenn@outlook.com
Requires-Python: >=3.7,<4.0
Classifier: License :: OSI Approved :: BSD License
Classifier: Programming Language :: Python :: 3
Classifier: Programming Language :: Python :: 3.7
Classifier: Programming Language :: Python :: 3.8
Classifier: Programming Language :: Python :: 3.9
Requires-Dist: django-tree-queries (>=0.7.0,<0.8.0)
Project-URL: Repository, https://github.com/jukanntenn/django-tree-comments
